ManoirAppLocalClient/ManoirAppLocalClient.py
ManoirAppLocalClient/__init__.py
manoir_app_local_client-0.1.0.dist-info/LICENSE
manoir_app_local_client-0.1.0.dist-info/METADATA
manoir_app_local_client-0.1.0.dist-info/WHEEL
manoir_app_local_client-0.1.0.dist-info/top_level.txt
manoir_app_local_client-0.1.0.dist-info/RECORD
