Metadata-Version: 2.1
Name: manoir-app-local-client
Version: 0.1.0
Author-email: "Manoir.app Team" <manoir.app@gmail.com>
Project-URL: Homepage, https://github.com/manoir-app/client-python
Project-URL: Bug Tracker, https://github.com/manoir-app/client-python/issues
Requires-Python: >=3.6
License-File: LICENSE
Requires-Dist: Requests >=2.3
